anymcp/__init__.py
anymcp/logger.py
anymcp/sse_to_stdio.py
anymcp/cli/__init__.py
anymcp/cli/anymcp.py
anymcp/cli/connect_command.py
anymcp-0.0.4.dist-info/METADATA
anymcp-0.0.4.dist-info/WHEEL
anymcp-0.0.4.dist-info/entry_points.txt
anymcp-0.0.4.dist-info/top_level.txt
anymcp-0.0.4.dist-info/RECORD
