Metadata-Version: 2.4
Name: anymcp
Version: 0.0.4
Summary: An adapter library for Model Context Protocol (MCP) SSE servers to connect as stdio
Author: Arcee AI
License: MIT
Project-URL: Repository, https://github.com/arcee-ai/anymcp
Classifier: Development Status :: 3 - Alpha
Classifier: Intended Audience :: Developers
Classifier: License :: OSI Approved :: MIT License
Classifier: Programming Language :: Python :: 3.7
Classifier: Programming Language :: Python :: 3.8
Classifier: Programming Language :: Python :: 3.9
Classifier: Programming Language :: Python :: 3.10
Classifier: Programming Language :: Python :: 3.11
Requires-Python: >=3.7
Requires-Dist: anyio
Requires-Dist: httpx
Requires-Dist: httpx_sse
Requires-Dist: sseclient-py
Requires-Dist: typing-extensions
Requires-Dist: mcp==1.9.2
Requires-Dist: loguru>=0.7.0
Provides-Extra: dev
Requires-Dist: pytest; extra == "dev"
Requires-Dist: pytest-asyncio; extra == "dev"
Requires-Dist: pytest-cov; extra == "dev"
Requires-Dist: black>=23.3.0; extra == "dev"
Requires-Dist: isort>=5.11.5; extra == "dev"
Requires-Dist: flake8; extra == "dev"
Requires-Dist: build; extra == "dev"
Requires-Dist: twine; extra == "dev"
